az/__init__.py
az/anthropic_provider.py
az/az.py
az/cache.py
az/chat_capture.py
az/config.py
az/gemini_provider.py
az/grok_provider.py
az/llm_provider.py
az/ollama_provider.py
az/openai_provider.py
az/utils.py
azc-1.4.0.dist-info/LICENSE
azc-1.4.0.dist-info/METADATA
azc-1.4.0.dist-info/WHEEL
azc-1.4.0.dist-info/entry_points.txt
azc-1.4.0.dist-info/top_level.txt
azc-1.4.0.dist-info/RECORD
