Metadata-Version: 2.1
Name: azc
Version: 1.4.0
Summary: Command-line tool for interacting with LLMs
Home-page: https://github.com/sagism/azc
Author: Sagi Smolarski
Author-email: sagism@gmail.com
Classifier: Programming Language :: Python :: 3
Classifier: License :: OSI Approved :: MIT License
Classifier: Operating System :: OS Independent
Requires-Python: >=3.6
License-File: LICENSE
Requires-Dist: openai ==1.45.0
Requires-Dist: prompt-toolkit ==3.0.47
Requires-Dist: python-dotenv ==1.0.1
Requires-Dist: rich ==13.8.1
Requires-Dist: anthropic ==0.49.0
Requires-Dist: google-generativeai ==0.8.1
Requires-Dist: pytest ==8.3.3
Requires-Dist: pytest-cov ==5.0.0
Requires-Dist: pre-commit ==3.8.0
